alibabacloud_rtc_white_board20201214/__init__.py
alibabacloud_rtc_white_board20201214/client.py
alibabacloud_rtc_white_board20201214/models.py
alibabacloud_rtc_white_board20201214_py2-2.0.5.dist-info/LICENSE
alibabacloud_rtc_white_board20201214_py2-2.0.5.dist-info/METADATA
alibabacloud_rtc_white_board20201214_py2-2.0.5.dist-info/WHEEL
alibabacloud_rtc_white_board20201214_py2-2.0.5.dist-info/top_level.txt
alibabacloud_rtc_white_board20201214_py2-2.0.5.dist-info/RECORD
